{
  "frames": {
    "sidebar": {
      "frame": {
        "x": 1,
        "y": 1,
        "w": 50,
        "h": 600
      },
      "rotated": false,
      "trimmed": false,
      "spriteSourceSize": {
        "x": 0,
        "y": 0,
        "w": 50,
        "h": 600
      },
      "sourceSize": {
        "w": 50,
        "h": 600
      },
      "pivot": {
        "x": 0.5,
        "y": 0.5
      }
    },
    "dentist_hand": {
      "frame": {
        "x": 1,
        "y": 603,
        "w": 200,
        "h": 250
      },
      "rotated": false,
      "trimmed": false,
      "spriteSourceSize": {
        "x": 0,
        "y": 0,
        "w": 200,
        "h": 250
      },
      "sourceSize": {
        "w": 200,
        "h": 250
      },
      "pivot": {
        "x": 0.5,
        "y": 0.5
      }
    },
    "ridiculous_death": {
      "frame": {
        "x": 1,
        "y": 855,
        "w": 50,
        "h": 150
      },
      "rotated": false,
      "trimmed": false,
      "spriteSourceSize": {
        "x": 0,
        "y": 0,
        "w": 50,
        "h": 150
      },
      "sourceSize": {
        "w": 50,
        "h": 150
      },
      "pivot": {
        "x": 0.5,
        "y": 0.5
      }
    },
    "bodyguard": {
      "frame": {
        "x": 1,
        "y": 1007,
        "w": 7,
        "h": 7
      },
      "rotated": false,
      "trimmed": false,
      "spriteSourceSize": {
        "x": 0,
        "y": 0,
        "w": 7,
        "h": 7
      },
      "sourceSize": {
        "w": 7,
        "h": 7
      },
      "pivot": {
        "x": 0.5,
        "y": 0.5
      }
    },
    "bullet": {
      "frame": {
        "x": 1,
        "y": 1016,
        "w": 10,
        "h": 3
      },
      "rotated": false,
      "trimmed": false,
      "spriteSourceSize": {
        "x": 0,
        "y": 0,
        "w": 10,
        "h": 3
      },
      "sourceSize": {
        "w": 10,
        "h": 3
      },
      "pivot": {
        "x": 0.5,
        "y": 0.5
      }
    },
    "explosion_01": {
      "frame": {
        "x": 53,
        "y": 855,
        "w": 96,
        "h": 95
      },
      "rotated": false,
      "trimmed": false,
      "spriteSourceSize": {
        "x": 0,
        "y": 0,
        "w": 96,
        "h": 95
      },
      "sourceSize": {
        "w": 96,
        "h": 95
      },
      "pivot": {
        "x": 0.5,
        "y": 0.5
      }
    },
    "bomb_60": {
      "frame": {
        "x": 53,
        "y": 952,
        "w": 49,
        "h": 51
      },
      "rotated": false,
      "trimmed": false,
      "spriteSourceSize": {
        "x": 0,
        "y": 0,
        "w": 49,
        "h": 51
      },
      "sourceSize": {
        "w": 49,
        "h": 51
      },
      "pivot": {
        "x": 0.5,
        "y": 0.5
      }
    },
    "bomb_30": {
      "frame": {
        "x": 104,
        "y": 952,
        "w": 51,
        "h": 50
      },
      "rotated": false,
      "trimmed": false,
      "spriteSourceSize": {
        "x": 0,
        "y": 0,
        "w": 51,
        "h": 50
      },
      "sourceSize": {
        "w": 51,
        "h": 50
      },
      "pivot": {
        "x": 0.5,
        "y": 0.5
      }
    },
    "explosion_02": {
      "frame": {
        "x": 151,
        "y": 855,
        "w": 96,
        "h": 95
      },
      "rotated": false,
      "trimmed": false,
      "spriteSourceSize": {
        "x": 0,
        "y": 0,
        "w": 96,
        "h": 95
      },
      "sourceSize": {
        "w": 96,
        "h": 95
      },
      "pivot": {
        "x": 0.5,
        "y": 0.5
      }
    },
    "automatic_slow_sidebar": {
      "frame": {
        "x": 157,
        "y": 952,
        "w": 40,
        "h": 40
      },
      "rotated": false,
      "trimmed": false,
      "spriteSourceSize": {
        "x": 0,
        "y": 0,
        "w": 40,
        "h": 40
      },
      "sourceSize": {
        "w": 40,
        "h": 40
      },
      "pivot": {
        "x": 0.5,
        "y": 0.5
      }
    },
    "automatic_slow": {
      "frame": {
        "x": 157,
        "y": 994,
        "w": 20,
        "h": 20
      },
      "rotated": false,
      "trimmed": false,
      "spriteSourceSize": {
        "x": 0,
        "y": 0,
        "w": 20,
        "h": 20
      },
      "sourceSize": {
        "w": 20,
        "h": 20
      },
      "pivot": {
        "x": 0.5,
        "y": 0.5
      }
    },
    "automatic_turbo": {
      "frame": {
        "x": 179,
        "y": 994,
        "w": 20,
        "h": 20
      },
      "rotated": false,
      "trimmed": false,
      "spriteSourceSize": {
        "x": 0,
        "y": 0,
        "w": 20,
        "h": 20
      },
      "sourceSize": {
        "w": 20,
        "h": 20
      },
      "pivot": {
        "x": 0.5,
        "y": 0.5
      }
    },
    "automatic_turbo_sidebar": {
      "frame": {
        "x": 199,
        "y": 952,
        "w": 40,
        "h": 40
      },
      "rotated": false,
      "trimmed": false,
      "spriteSourceSize": {
        "x": 0,
        "y": 0,
        "w": 40,
        "h": 40
      },
      "sourceSize": {
        "w": 40,
        "h": 40
      },
      "pivot": {
        "x": 0.5,
        "y": 0.5
      }
    },
    "bodyguard_item": {
      "frame": {
        "x": 201,
        "y": 994,
        "w": 20,
        "h": 20
      },
      "rotated": false,
      "trimmed": false,
      "spriteSourceSize": {
        "x": 0,
        "y": 0,
        "w": 20,
        "h": 20
      },
      "sourceSize": {
        "w": 20,
        "h": 20
      },
      "pivot": {
        "x": 0.5,
        "y": 0.5
      }
    },
    "bomb": {
      "frame": {
        "x": 223,
        "y": 994,
        "w": 20,
        "h": 20
      },
      "rotated": false,
      "trimmed": false,
      "spriteSourceSize": {
        "x": 0,
        "y": 0,
        "w": 20,
        "h": 20
      },
      "sourceSize": {
        "w": 20,
        "h": 20
      },
      "pivot": {
        "x": 0.5,
        "y": 0.5
      }
    },
    "crossing_sidebar": {
      "frame": {
        "x": 241,
        "y": 952,
        "w": 40,
        "h": 40
      },
      "rotated": false,
      "trimmed": false,
      "spriteSourceSize": {
        "x": 0,
        "y": 0,
        "w": 40,
        "h": 40
      },
      "sourceSize": {
        "w": 40,
        "h": 40
      },
      "pivot": {
        "x": 0.5,
        "y": 0.5
      }
    },
    "crossing": {
      "frame": {
        "x": 245,
        "y": 994,
        "w": 20,
        "h": 20
      },
      "rotated": false,
      "trimmed": false,
      "spriteSourceSize": {
        "x": 0,
        "y": 0,
        "w": 20,
        "h": 20
      },
      "sourceSize": {
        "w": 20,
        "h": 20
      },
      "pivot": {
        "x": 0.5,
        "y": 0.5
      }
    },
    "eraser": {
      "frame": {
        "x": 267,
        "y": 994,
        "w": 20,
        "h": 20
      },
      "rotated": false,
      "trimmed": false,
      "spriteSourceSize": {
        "x": 0,
        "y": 0,
        "w": 20,
        "h": 20
      },
      "sourceSize": {
        "w": 20,
        "h": 20
      },
      "pivot": {
        "x": 0.5,
        "y": 0.5
      }
    },
    "explosion_03": {
      "frame": {
        "x": 53,
        "y": 1,
        "w": 96,
        "h": 95
      },
      "rotated": false,
      "trimmed": false,
      "spriteSourceSize": {
        "x": 0,
        "y": 0,
        "w": 96,
        "h": 95
      },
      "sourceSize": {
        "w": 96,
        "h": 95
      },
      "pivot": {
        "x": 0.5,
        "y": 0.5
      }
    },
    "explosion_04": {
      "frame": {
        "x": 53,
        "y": 98,
        "w": 96,
        "h": 95
      },
      "rotated": false,
      "trimmed": false,
      "spriteSourceSize": {
        "x": 0,
        "y": 0,
        "w": 96,
        "h": 95
      },
      "sourceSize": {
        "w": 96,
        "h": 95
      },
      "pivot": {
        "x": 0.5,
        "y": 0.5
      }
    },
    "explosion_05": {
      "frame": {
        "x": 53,
        "y": 195,
        "w": 96,
        "h": 95
      },
      "rotated": false,
      "trimmed": false,
      "spriteSourceSize": {
        "x": 0,
        "y": 0,
        "w": 96,
        "h": 95
      },
      "sourceSize": {
        "w": 96,
        "h": 95
      },
      "pivot": {
        "x": 0.5,
        "y": 0.5
      }
    },
    "explosion_06": {
      "frame": {
        "x": 53,
        "y": 292,
        "w": 96,
        "h": 95
      },
      "rotated": false,
      "trimmed": false,
      "spriteSourceSize": {
        "x": 0,
        "y": 0,
        "w": 96,
        "h": 95
      },
      "sourceSize": {
        "w": 96,
        "h": 95
      },
      "pivot": {
        "x": 0.5,
        "y": 0.5
      }
    },
    "explosion_07": {
      "frame": {
        "x": 53,
        "y": 389,
        "w": 96,
        "h": 95
      },
      "rotated": false,
      "trimmed": false,
      "spriteSourceSize": {
        "x": 0,
        "y": 0,
        "w": 96,
        "h": 95
      },
      "sourceSize": {
        "w": 96,
        "h": 95
      },
      "pivot": {
        "x": 0.5,
        "y": 0.5
      }
    },
    "explosion_08": {
      "frame": {
        "x": 53,
        "y": 486,
        "w": 96,
        "h": 95
      },
      "rotated": false,
      "trimmed": false,
      "spriteSourceSize": {
        "x": 0,
        "y": 0,
        "w": 96,
        "h": 95
      },
      "sourceSize": {
        "w": 96,
        "h": 95
      },
      "pivot": {
        "x": 0.5,
        "y": 0.5
      }
    },
    "explosion_09": {
      "frame": {
        "x": 151,
        "y": 1,
        "w": 96,
        "h": 95
      },
      "rotated": false,
      "trimmed": false,
      "spriteSourceSize": {
        "x": 0,
        "y": 0,
        "w": 96,
        "h": 95
      },
      "sourceSize": {
        "w": 96,
        "h": 95
      },
      "pivot": {
        "x": 0.5,
        "y": 0.5
      }
    },
    "explosion_10": {
      "frame": {
        "x": 151,
        "y": 98,
        "w": 96,
        "h": 95
      },
      "rotated": false,
      "trimmed": false,
      "spriteSourceSize": {
        "x": 0,
        "y": 0,
        "w": 96,
        "h": 95
      },
      "sourceSize": {
        "w": 96,
        "h": 95
      },
      "pivot": {
        "x": 0.5,
        "y": 0.5
      }
    },
    "explosion_11": {
      "frame": {
        "x": 151,
        "y": 195,
        "w": 96,
        "h": 95
      },
      "rotated": false,
      "trimmed": false,
      "spriteSourceSize": {
        "x": 0,
        "y": 0,
        "w": 96,
        "h": 95
      },
      "sourceSize": {
        "w": 96,
        "h": 95
      },
      "pivot": {
        "x": 0.5,
        "y": 0.5
      }
    },
    "explosion_12": {
      "frame": {
        "x": 151,
        "y": 292,
        "w": 96,
        "h": 95
      },
      "rotated": false,
      "trimmed": false,
      "spriteSourceSize": {
        "x": 0,
        "y": 0,
        "w": 96,
        "h": 95
      },
      "sourceSize": {
        "w": 96,
        "h": 95
      },
      "pivot": {
        "x": 0.5,
        "y": 0.5
      }
    },
    "explosion_13": {
      "frame": {
        "x": 151,
        "y": 389,
        "w": 96,
        "h": 95
      },
      "rotated": false,
      "trimmed": false,
      "spriteSourceSize": {
        "x": 0,
        "y": 0,
        "w": 96,
        "h": 95
      },
      "sourceSize": {
        "w": 96,
        "h": 95
      },
      "pivot": {
        "x": 0.5,
        "y": 0.5
      }
    },
    "explosion_14": {
      "frame": {
        "x": 151,
        "y": 486,
        "w": 96,
        "h": 95
      },
      "rotated": false,
      "trimmed": false,
      "spriteSourceSize": {
        "x": 0,
        "y": 0,
        "w": 96,
        "h": 95
      },
      "sourceSize": {
        "w": 96,
        "h": 95
      },
      "pivot": {
        "x": 0.5,
        "y": 0.5
      }
    },
    "explosion_15": {
      "frame": {
        "x": 203,
        "y": 583,
        "w": 96,
        "h": 95
      },
      "rotated": false,
      "trimmed": false,
      "spriteSourceSize": {
        "x": 0,
        "y": 0,
        "w": 96,
        "h": 95
      },
      "sourceSize": {
        "w": 96,
        "h": 95
      },
      "pivot": {
        "x": 0.5,
        "y": 0.5
      }
    },
    "explosion_16": {
      "frame": {
        "x": 203,
        "y": 680,
        "w": 96,
        "h": 95
      },
      "rotated": false,
      "trimmed": false,
      "spriteSourceSize": {
        "x": 0,
        "y": 0,
        "w": 96,
        "h": 95
      },
      "sourceSize": {
        "w": 96,
        "h": 95
      },
      "pivot": {
        "x": 0.5,
        "y": 0.5
      }
    },
    "eraser_sidebar": {
      "frame": {
        "x": 203,
        "y": 777,
        "w": 40,
        "h": 40
      },
      "rotated": false,
      "trimmed": false,
      "spriteSourceSize": {
        "x": 0,
        "y": 0,
        "w": 40,
        "h": 40
      },
      "sourceSize": {
        "w": 40,
        "h": 40
      },
      "pivot": {
        "x": 0.5,
        "y": 0.5
      }
    },
    "bomb_0": {
      "frame": {
        "x": 203,
        "y": 819,
        "w": 38,
        "h": 34
      },
      "rotated": false,
      "trimmed": false,
      "spriteSourceSize": {
        "x": 0,
        "y": 0,
        "w": 38,
        "h": 34
      },
      "sourceSize": {
        "w": 38,
        "h": 34
      },
      "pivot": {
        "x": 0.5,
        "y": 0.5
      }
    },
    "color_blind_to_left": {
      "frame": {
        "x": 243,
        "y": 819,
        "w": 200,
        "h": 30
      },
      "rotated": false,
      "trimmed": false,
      "spriteSourceSize": {
        "x": 0,
        "y": 0,
        "w": 200,
        "h": 30
      },
      "sourceSize": {
        "w": 200,
        "h": 30
      },
      "pivot": {
        "x": 0.5,
        "y": 0.5
      }
    },
    "glock_sidebar": {
      "frame": {
        "x": 245,
        "y": 777,
        "w": 40,
        "h": 40
      },
      "rotated": false,
      "trimmed": false,
      "spriteSourceSize": {
        "x": 0,
        "y": 0,
        "w": 40,
        "h": 40
      },
      "sourceSize": {
        "w": 40,
        "h": 40
      },
      "pivot": {
        "x": 0.5,
        "y": 0.5
      }
    },
    "lock_borders_sidebar": {
      "frame": {
        "x": 287,
        "y": 777,
        "w": 40,
        "h": 40
      },
      "rotated": false,
      "trimmed": false,
      "spriteSourceSize": {
        "x": 0,
        "y": 0,
        "w": 40,
        "h": 40
      },
      "sourceSize": {
        "w": 40,
        "h": 40
      },
      "pivot": {
        "x": 0.5,
        "y": 0.5
      }
    },
    "explosion_17": {
      "frame": {
        "x": 249,
        "y": 851,
        "w": 96,
        "h": 95
      },
      "rotated": false,
      "trimmed": false,
      "spriteSourceSize": {
        "x": 0,
        "y": 0,
        "w": 96,
        "h": 95
      },
      "sourceSize": {
        "w": 96,
        "h": 95
      },
      "pivot": {
        "x": 0.5,
        "y": 0.5
      }
    },
    "portal_01": {
      "frame": {
        "x": 283,
        "y": 948,
        "w": 40,
        "h": 40
      },
      "rotated": false,
      "trimmed": false,
      "spriteSourceSize": {
        "x": 0,
        "y": 0,
        "w": 40,
        "h": 40
      },
      "sourceSize": {
        "w": 40,
        "h": 40
      },
      "pivot": {
        "x": 0.5,
        "y": 0.5
      }
    },
    "color_blind_to_right": {
      "frame": {
        "x": 289,
        "y": 990,
        "w": 200,
        "h": 30
      },
      "rotated": false,
      "trimmed": false,
      "spriteSourceSize": {
        "x": 0,
        "y": 0,
        "w": 200,
        "h": 30
      },
      "sourceSize": {
        "w": 200,
        "h": 30
      },
      "pivot": {
        "x": 0.5,
        "y": 0.5
      }
    },
    "portal_02": {
      "frame": {
        "x": 325,
        "y": 948,
        "w": 40,
        "h": 40
      },
      "rotated": false,
      "trimmed": false,
      "spriteSourceSize": {
        "x": 0,
        "y": 0,
        "w": 40,
        "h": 40
      },
      "sourceSize": {
        "w": 40,
        "h": 40
      },
      "pivot": {
        "x": 0.5,
        "y": 0.5
      }
    },
    "explosion_18": {
      "frame": {
        "x": 347,
        "y": 851,
        "w": 96,
        "h": 95
      },
      "rotated": false,
      "trimmed": false,
      "spriteSourceSize": {
        "x": 0,
        "y": 0,
        "w": 96,
        "h": 95
      },
      "sourceSize": {
        "w": 96,
        "h": 95
      },
      "pivot": {
        "x": 0.5,
        "y": 0.5
      }
    },
    "portal_03": {
      "frame": {
        "x": 367,
        "y": 948,
        "w": 40,
        "h": 40
      },
      "rotated": false,
      "trimmed": false,
      "spriteSourceSize": {
        "x": 0,
        "y": 0,
        "w": 40,
        "h": 40
      },
      "sourceSize": {
        "w": 40,
        "h": 40
      },
      "pivot": {
        "x": 0.5,
        "y": 0.5
      }
    },
    "portal_04": {
      "frame": {
        "x": 409,
        "y": 948,
        "w": 40,
        "h": 40
      },
      "rotated": false,
      "trimmed": false,
      "spriteSourceSize": {
        "x": 0,
        "y": 0,
        "w": 40,
        "h": 40
      },
      "sourceSize": {
        "w": 40,
        "h": 40
      },
      "pivot": {
        "x": 0.5,
        "y": 0.5
      }
    },
    "explosion_19": {
      "frame": {
        "x": 491,
        "y": 1,
        "w": 96,
        "h": 95
      },
      "rotated": false,
      "trimmed": false,
      "spriteSourceSize": {
        "x": 0,
        "y": 0,
        "w": 96,
        "h": 95
      },
      "sourceSize": {
        "w": 96,
        "h": 95
      },
      "pivot": {
        "x": 0.5,
        "y": 0.5
      }
    },
    "portal_05": {
      "frame": {
        "x": 445,
        "y": 1,
        "w": 40,
        "h": 40
      },
      "rotated": false,
      "trimmed": false,
      "spriteSourceSize": {
        "x": 0,
        "y": 0,
        "w": 40,
        "h": 40
      },
      "sourceSize": {
        "w": 40,
        "h": 40
      },
      "pivot": {
        "x": 0.5,
        "y": 0.5
      }
    },
    "portal_06": {
      "frame": {
        "x": 445,
        "y": 43,
        "w": 40,
        "h": 40
      },
      "rotated": false,
      "trimmed": false,
      "spriteSourceSize": {
        "x": 0,
        "y": 0,
        "w": 40,
        "h": 40
      },
      "sourceSize": {
        "w": 40,
        "h": 40
      },
      "pivot": {
        "x": 0.5,
        "y": 0.5
      }
    },
    "portal_07": {
      "frame": {
        "x": 445,
        "y": 85,
        "w": 40,
        "h": 40
      },
      "rotated": false,
      "trimmed": false,
      "spriteSourceSize": {
        "x": 0,
        "y": 0,
        "w": 40,
        "h": 40
      },
      "sourceSize": {
        "w": 40,
        "h": 40
      },
      "pivot": {
        "x": 0.5,
        "y": 0.5
      }
    },
    "portal_08": {
      "frame": {
        "x": 445,
        "y": 127,
        "w": 40,
        "h": 40
      },
      "rotated": false,
      "trimmed": false,
      "spriteSourceSize": {
        "x": 0,
        "y": 0,
        "w": 40,
        "h": 40
      },
      "sourceSize": {
        "w": 40,
        "h": 40
      },
      "pivot": {
        "x": 0.5,
        "y": 0.5
      }
    },
    "explosion_20": {
      "frame": {
        "x": 329,
        "y": 1,
        "w": 96,
        "h": 95
      },
      "rotated": false,
      "trimmed": false,
      "spriteSourceSize": {
        "x": 0,
        "y": 0,
        "w": 96,
        "h": 95
      },
      "sourceSize": {
        "w": 96,
        "h": 95
      },
      "pivot": {
        "x": 0.5,
        "y": 0.5
      }
    },
    "glock": {
      "frame": {
        "x": 301,
        "y": 1,
        "w": 20,
        "h": 20
      },
      "rotated": false,
      "trimmed": false,
      "spriteSourceSize": {
        "x": 0,
        "y": 0,
        "w": 20,
        "h": 20
      },
      "sourceSize": {
        "w": 20,
        "h": 20
      },
      "pivot": {
        "x": 0.5,
        "y": 0.5
      }
    },
    "lock_borders": {
      "frame": {
        "x": 301,
        "y": 23,
        "w": 20,
        "h": 20
      },
      "rotated": false,
      "trimmed": false,
      "spriteSourceSize": {
        "x": 0,
        "y": 0,
        "w": 20,
        "h": 20
      },
      "sourceSize": {
        "w": 20,
        "h": 20
      },
      "pivot": {
        "x": 0.5,
        "y": 0.5
      }
    },
    "random_item": {
      "frame": {
        "x": 301,
        "y": 45,
        "w": 20,
        "h": 20
      },
      "rotated": false,
      "trimmed": false,
      "spriteSourceSize": {
        "x": 0,
        "y": 0,
        "w": 20,
        "h": 20
      },
      "sourceSize": {
        "w": 20,
        "h": 20
      },
      "pivot": {
        "x": 0.5,
        "y": 0.5
      }
    },
    "reverse": {
      "frame": {
        "x": 301,
        "y": 67,
        "w": 20,
        "h": 20
      },
      "rotated": false,
      "trimmed": false,
      "spriteSourceSize": {
        "x": 0,
        "y": 0,
        "w": 20,
        "h": 20
      },
      "sourceSize": {
        "w": 20,
        "h": 20
      },
      "pivot": {
        "x": 0.5,
        "y": 0.5
      }
    },
    "rifle": {
      "frame": {
        "x": 301,
        "y": 89,
        "w": 20,
        "h": 20
      },
      "rotated": false,
      "trimmed": false,
      "spriteSourceSize": {
        "x": 0,
        "y": 0,
        "w": 20,
        "h": 20
      },
      "sourceSize": {
        "w": 20,
        "h": 20
      },
      "pivot": {
        "x": 0.5,
        "y": 0.5
      }
    },
    "shield": {
      "frame": {
        "x": 301,
        "y": 111,
        "w": 20,
        "h": 20
      },
      "rotated": false,
      "trimmed": false,
      "spriteSourceSize": {
        "x": 0,
        "y": 0,
        "w": 20,
        "h": 20
      },
      "sourceSize": {
        "w": 20,
        "h": 20
      },
      "pivot": {
        "x": 0.5,
        "y": 0.5
      }
    },
    "portal_09": {
      "frame": {
        "x": 249,
        "y": 1,
        "w": 40,
        "h": 40
      },
      "rotated": false,
      "trimmed": false,
      "spriteSourceSize": {
        "x": 0,
        "y": 0,
        "w": 40,
        "h": 40
      },
      "sourceSize": {
        "w": 40,
        "h": 40
      },
      "pivot": {
        "x": 0.5,
        "y": 0.5
      }
    },
    "portal_10": {
      "frame": {
        "x": 249,
        "y": 43,
        "w": 40,
        "h": 40
      },
      "rotated": false,
      "trimmed": false,
      "spriteSourceSize": {
        "x": 0,
        "y": 0,
        "w": 40,
        "h": 40
      },
      "sourceSize": {
        "w": 40,
        "h": 40
      },
      "pivot": {
        "x": 0.5,
        "y": 0.5
      }
    },
    "portal_11": {
      "frame": {
        "x": 249,
        "y": 85,
        "w": 40,
        "h": 40
      },
      "rotated": false,
      "trimmed": false,
      "spriteSourceSize": {
        "x": 0,
        "y": 0,
        "w": 40,
        "h": 40
      },
      "sourceSize": {
        "w": 40,
        "h": 40
      },
      "pivot": {
        "x": 0.5,
        "y": 0.5
      }
    },
    "portal_12": {
      "frame": {
        "x": 249,
        "y": 127,
        "w": 40,
        "h": 40
      },
      "rotated": false,
      "trimmed": false,
      "spriteSourceSize": {
        "x": 0,
        "y": 0,
        "w": 40,
        "h": 40
      },
      "sourceSize": {
        "w": 40,
        "h": 40
      },
      "pivot": {
        "x": 0.5,
        "y": 0.5
      }
    },
    "explosion_21": {
      "frame": {
        "x": 329,
        "y": 98,
        "w": 96,
        "h": 95
      },
      "rotated": false,
      "trimmed": false,
      "spriteSourceSize": {
        "x": 0,
        "y": 0,
        "w": 96,
        "h": 95
      },
      "sourceSize": {
        "w": 96,
        "h": 95
      },
      "pivot": {
        "x": 0.5,
        "y": 0.5
      }
    },
    "bomb_90": {
      "frame": {
        "x": 291,
        "y": 133,
        "w": 34,
        "h": 38
      },
      "rotated": false,
      "trimmed": false,
      "spriteSourceSize": {
        "x": 0,
        "y": 0,
        "w": 34,
        "h": 38
      },
      "sourceSize": {
        "w": 34,
        "h": 38
      },
      "pivot": {
        "x": 0.5,
        "y": 0.5
      }
    },
    "portal_13": {
      "frame": {
        "x": 249,
        "y": 169,
        "w": 40,
        "h": 40
      },
      "rotated": false,
      "trimmed": false,
      "spriteSourceSize": {
        "x": 0,
        "y": 0,
        "w": 40,
        "h": 40
      },
      "sourceSize": {
        "w": 40,
        "h": 40
      },
      "pivot": {
        "x": 0.5,
        "y": 0.5
      }
    },
    "bomb_sidebar": {
      "frame": {
        "x": 291,
        "y": 173,
        "w": 34,
        "h": 38
      },
      "rotated": false,
      "trimmed": false,
      "spriteSourceSize": {
        "x": 0,
        "y": 0,
        "w": 34,
        "h": 38
      },
      "sourceSize": {
        "w": 34,
        "h": 38
      },
      "pivot": {
        "x": 0.5,
        "y": 0.5
      }
    },
    "portal_14": {
      "frame": {
        "x": 249,
        "y": 211,
        "w": 40,
        "h": 40
      },
      "rotated": false,
      "trimmed": false,
      "spriteSourceSize": {
        "x": 0,
        "y": 0,
        "w": 40,
        "h": 40
      },
      "sourceSize": {
        "w": 40,
        "h": 40
      },
      "pivot": {
        "x": 0.5,
        "y": 0.5
      }
    },
    "explosion_22": {
      "frame": {
        "x": 249,
        "y": 253,
        "w": 96,
        "h": 95
      },
      "rotated": false,
      "trimmed": false,
      "spriteSourceSize": {
        "x": 0,
        "y": 0,
        "w": 96,
        "h": 95
      },
      "sourceSize": {
        "w": 96,
        "h": 95
      },
      "pivot": {
        "x": 0.5,
        "y": 0.5
      }
    },
    "portal_15": {
      "frame": {
        "x": 327,
        "y": 195,
        "w": 40,
        "h": 40
      },
      "rotated": false,
      "trimmed": false,
      "spriteSourceSize": {
        "x": 0,
        "y": 0,
        "w": 40,
        "h": 40
      },
      "sourceSize": {
        "w": 40,
        "h": 40
      },
      "pivot": {
        "x": 0.5,
        "y": 0.5
      }
    },
    "shotgun": {
      "frame": {
        "x": 291,
        "y": 213,
        "w": 20,
        "h": 20
      },
      "rotated": false,
      "trimmed": false,
      "spriteSourceSize": {
        "x": 0,
        "y": 0,
        "w": 20,
        "h": 20
      },
      "sourceSize": {
        "w": 20,
        "h": 20
      },
      "pivot": {
        "x": 0.5,
        "y": 0.5
      }
    },
    "explosion_23": {
      "frame": {
        "x": 249,
        "y": 350,
        "w": 96,
        "h": 95
      },
      "rotated": false,
      "trimmed": false,
      "spriteSourceSize": {
        "x": 0,
        "y": 0,
        "w": 96,
        "h": 95
      },
      "sourceSize": {
        "w": 96,
        "h": 95
      },
      "pivot": {
        "x": 0.5,
        "y": 0.5
      }
    },
    "explosion_24": {
      "frame": {
        "x": 249,
        "y": 447,
        "w": 96,
        "h": 95
      },
      "rotated": false,
      "trimmed": false,
      "spriteSourceSize": {
        "x": 0,
        "y": 0,
        "w": 96,
        "h": 95
      },
      "sourceSize": {
        "w": 96,
        "h": 95
      },
      "pivot": {
        "x": 0.5,
        "y": 0.5
      }
    },
    "slow": {
      "frame": {
        "x": 249,
        "y": 544,
        "w": 20,
        "h": 20
      },
      "rotated": false,
      "trimmed": false,
      "spriteSourceSize": {
        "x": 0,
        "y": 0,
        "w": 20,
        "h": 20
      },
      "sourceSize": {
        "w": 20,
        "h": 20
      },
      "pivot": {
        "x": 0.5,
        "y": 0.5
      }
    },
    "turbo": {
      "frame": {
        "x": 271,
        "y": 544,
        "w": 20,
        "h": 20
      },
      "rotated": false,
      "trimmed": false,
      "spriteSourceSize": {
        "x": 0,
        "y": 0,
        "w": 20,
        "h": 20
      },
      "sourceSize": {
        "w": 20,
        "h": 20
      },
      "pivot": {
        "x": 0.5,
        "y": 0.5
      }
    },
    "uzi": {
      "frame": {
        "x": 293,
        "y": 544,
        "w": 20,
        "h": 20
      },
      "rotated": false,
      "trimmed": false,
      "spriteSourceSize": {
        "x": 0,
        "y": 0,
        "w": 20,
        "h": 20
      },
      "sourceSize": {
        "w": 20,
        "h": 20
      },
      "pivot": {
        "x": 0.5,
        "y": 0.5
      }
    },
    "explosion_25": {
      "frame": {
        "x": 301,
        "y": 566,
        "w": 96,
        "h": 95
      },
      "rotated": false,
      "trimmed": false,
      "spriteSourceSize": {
        "x": 0,
        "y": 0,
        "w": 96,
        "h": 95
      },
      "sourceSize": {
        "w": 96,
        "h": 95
      },
      "pivot": {
        "x": 0.5,
        "y": 0.5
      }
    },
    "explosion_26": {
      "frame": {
        "x": 301,
        "y": 663,
        "w": 96,
        "h": 95
      },
      "rotated": false,
      "trimmed": false,
      "spriteSourceSize": {
        "x": 0,
        "y": 0,
        "w": 96,
        "h": 95
      },
      "sourceSize": {
        "w": 96,
        "h": 95
      },
      "pivot": {
        "x": 0.5,
        "y": 0.5
      }
    },
    "portal_16": {
      "frame": {
        "x": 329,
        "y": 760,
        "w": 40,
        "h": 40
      },
      "rotated": false,
      "trimmed": false,
      "spriteSourceSize": {
        "x": 0,
        "y": 0,
        "w": 40,
        "h": 40
      },
      "sourceSize": {
        "w": 40,
        "h": 40
      },
      "pivot": {
        "x": 0.5,
        "y": 0.5
      }
    },
    "portal_17": {
      "frame": {
        "x": 371,
        "y": 760,
        "w": 40,
        "h": 40
      },
      "rotated": false,
      "trimmed": false,
      "spriteSourceSize": {
        "x": 0,
        "y": 0,
        "w": 40,
        "h": 40
      },
      "sourceSize": {
        "w": 40,
        "h": 40
      },
      "pivot": {
        "x": 0.5,
        "y": 0.5
      }
    },
    "explosion_27": {
      "frame": {
        "x": 347,
        "y": 237,
        "w": 96,
        "h": 95
      },
      "rotated": false,
      "trimmed": false,
      "spriteSourceSize": {
        "x": 0,
        "y": 0,
        "w": 96,
        "h": 95
      },
      "sourceSize": {
        "w": 96,
        "h": 95
      },
      "pivot": {
        "x": 0.5,
        "y": 0.5
      }
    },
    "portal_18": {
      "frame": {
        "x": 369,
        "y": 195,
        "w": 40,
        "h": 40
      },
      "rotated": false,
      "trimmed": false,
      "spriteSourceSize": {
        "x": 0,
        "y": 0,
        "w": 40,
        "h": 40
      },
      "sourceSize": {
        "w": 40,
        "h": 40
      },
      "pivot": {
        "x": 0.5,
        "y": 0.5
      }
    },
    "portal_19": {
      "frame": {
        "x": 411,
        "y": 195,
        "w": 40,
        "h": 40
      },
      "rotated": false,
      "trimmed": false,
      "spriteSourceSize": {
        "x": 0,
        "y": 0,
        "w": 40,
        "h": 40
      },
      "sourceSize": {
        "w": 40,
        "h": 40
      },
      "pivot": {
        "x": 0.5,
        "y": 0.5
      }
    },
    "portal_20": {
      "frame": {
        "x": 453,
        "y": 195,
        "w": 40,
        "h": 40
      },
      "rotated": false,
      "trimmed": false,
      "spriteSourceSize": {
        "x": 0,
        "y": 0,
        "w": 40,
        "h": 40
      },
      "sourceSize": {
        "w": 40,
        "h": 40
      },
      "pivot": {
        "x": 0.5,
        "y": 0.5
      }
    },
    "explosion_28": {
      "frame": {
        "x": 487,
        "y": 98,
        "w": 96,
        "h": 95
      },
      "rotated": false,
      "trimmed": false,
      "spriteSourceSize": {
        "x": 0,
        "y": 0,
        "w": 96,
        "h": 95
      },
      "sourceSize": {
        "w": 96,
        "h": 95
      },
      "pivot": {
        "x": 0.5,
        "y": 0.5
      }
    },
    "explosion_29": {
      "frame": {
        "x": 347,
        "y": 334,
        "w": 96,
        "h": 95
      },
      "rotated": false,
      "trimmed": false,
      "spriteSourceSize": {
        "x": 0,
        "y": 0,
        "w": 96,
        "h": 95
      },
      "sourceSize": {
        "w": 96,
        "h": 95
      },
      "pivot": {
        "x": 0.5,
        "y": 0.5
      }
    },
    "explosion_30": {
      "frame": {
        "x": 347,
        "y": 431,
        "w": 96,
        "h": 95
      },
      "rotated": false,
      "trimmed": false,
      "spriteSourceSize": {
        "x": 0,
        "y": 0,
        "w": 96,
        "h": 95
      },
      "sourceSize": {
        "w": 96,
        "h": 95
      },
      "pivot": {
        "x": 0.5,
        "y": 0.5
      }
    },
    "explosion_31": {
      "frame": {
        "x": 399,
        "y": 528,
        "w": 96,
        "h": 95
      },
      "rotated": false,
      "trimmed": false,
      "spriteSourceSize": {
        "x": 0,
        "y": 0,
        "w": 96,
        "h": 95
      },
      "sourceSize": {
        "w": 96,
        "h": 95
      },
      "pivot": {
        "x": 0.5,
        "y": 0.5
      }
    },
    "explosion_32": {
      "frame": {
        "x": 399,
        "y": 625,
        "w": 96,
        "h": 95
      },
      "rotated": false,
      "trimmed": false,
      "spriteSourceSize": {
        "x": 0,
        "y": 0,
        "w": 96,
        "h": 95
      },
      "sourceSize": {
        "w": 96,
        "h": 95
      },
      "pivot": {
        "x": 0.5,
        "y": 0.5
      }
    },
    "explosion_33": {
      "frame": {
        "x": 413,
        "y": 722,
        "w": 96,
        "h": 95
      },
      "rotated": false,
      "trimmed": false,
      "spriteSourceSize": {
        "x": 0,
        "y": 0,
        "w": 96,
        "h": 95
      },
      "sourceSize": {
        "w": 96,
        "h": 95
      },
      "pivot": {
        "x": 0.5,
        "y": 0.5
      }
    },
    "explosion_34": {
      "frame": {
        "x": 511,
        "y": 722,
        "w": 96,
        "h": 95
      },
      "rotated": false,
      "trimmed": false,
      "spriteSourceSize": {
        "x": 0,
        "y": 0,
        "w": 96,
        "h": 95
      },
      "sourceSize": {
        "w": 96,
        "h": 95
      },
      "pivot": {
        "x": 0.5,
        "y": 0.5
      }
    },
    "explosion_35": {
      "frame": {
        "x": 445,
        "y": 819,
        "w": 96,
        "h": 95
      },
      "rotated": false,
      "trimmed": false,
      "spriteSourceSize": {
        "x": 0,
        "y": 0,
        "w": 96,
        "h": 95
      },
      "sourceSize": {
        "w": 96,
        "h": 95
      },
      "pivot": {
        "x": 0.5,
        "y": 0.5
      }
    },
    "explosion_36": {
      "frame": {
        "x": 491,
        "y": 916,
        "w": 96,
        "h": 95
      },
      "rotated": false,
      "trimmed": false,
      "spriteSourceSize": {
        "x": 0,
        "y": 0,
        "w": 96,
        "h": 95
      },
      "sourceSize": {
        "w": 96,
        "h": 95
      },
      "pivot": {
        "x": 0.5,
        "y": 0.5
      }
    },
    "explosion_37": {
      "frame": {
        "x": 543,
        "y": 819,
        "w": 96,
        "h": 95
      },
      "rotated": false,
      "trimmed": false,
      "spriteSourceSize": {
        "x": 0,
        "y": 0,
        "w": 96,
        "h": 95
      },
      "sourceSize": {
        "w": 96,
        "h": 95
      },
      "pivot": {
        "x": 0.5,
        "y": 0.5
      }
    },
    "explosion_38": {
      "frame": {
        "x": 589,
        "y": 916,
        "w": 96,
        "h": 95
      },
      "rotated": false,
      "trimmed": false,
      "spriteSourceSize": {
        "x": 0,
        "y": 0,
        "w": 96,
        "h": 95
      },
      "sourceSize": {
        "w": 96,
        "h": 95
      },
      "pivot": {
        "x": 0.5,
        "y": 0.5
      }
    },
    "explosion_39": {
      "frame": {
        "x": 687,
        "y": 819,
        "w": 96,
        "h": 95
      },
      "rotated": false,
      "trimmed": false,
      "spriteSourceSize": {
        "x": 0,
        "y": 0,
        "w": 96,
        "h": 95
      },
      "sourceSize": {
        "w": 96,
        "h": 95
      },
      "pivot": {
        "x": 0.5,
        "y": 0.5
      }
    },
    "portal_21": {
      "frame": {
        "x": 641,
        "y": 1,
        "w": 40,
        "h": 40
      },
      "rotated": false,
      "trimmed": false,
      "spriteSourceSize": {
        "x": 0,
        "y": 0,
        "w": 40,
        "h": 40
      },
      "sourceSize": {
        "w": 40,
        "h": 40
      },
      "pivot": {
        "x": 0.5,
        "y": 0.5
      }
    },
    "portal_22": {
      "frame": {
        "x": 641,
        "y": 43,
        "w": 40,
        "h": 40
      },
      "rotated": false,
      "trimmed": false,
      "spriteSourceSize": {
        "x": 0,
        "y": 0,
        "w": 40,
        "h": 40
      },
      "sourceSize": {
        "w": 40,
        "h": 40
      },
      "pivot": {
        "x": 0.5,
        "y": 0.5
      }
    },
    "portal_23": {
      "frame": {
        "x": 641,
        "y": 85,
        "w": 40,
        "h": 40
      },
      "rotated": false,
      "trimmed": false,
      "spriteSourceSize": {
        "x": 0,
        "y": 0,
        "w": 40,
        "h": 40
      },
      "sourceSize": {
        "w": 40,
        "h": 40
      },
      "pivot": {
        "x": 0.5,
        "y": 0.5
      }
    },
    "portal_24": {
      "frame": {
        "x": 641,
        "y": 127,
        "w": 40,
        "h": 40
      },
      "rotated": false,
      "trimmed": false,
      "spriteSourceSize": {
        "x": 0,
        "y": 0,
        "w": 40,
        "h": 40
      },
      "sourceSize": {
        "w": 40,
        "h": 40
      },
      "pivot": {
        "x": 0.5,
        "y": 0.5
      }
    },
    "portal_25": {
      "frame": {
        "x": 641,
        "y": 169,
        "w": 40,
        "h": 40
      },
      "rotated": false,
      "trimmed": false,
      "spriteSourceSize": {
        "x": 0,
        "y": 0,
        "w": 40,
        "h": 40
      },
      "sourceSize": {
        "w": 40,
        "h": 40
      },
      "pivot": {
        "x": 0.5,
        "y": 0.5
      }
    },
    "portal_26": {
      "frame": {
        "x": 641,
        "y": 211,
        "w": 40,
        "h": 40
      },
      "rotated": false,
      "trimmed": false,
      "spriteSourceSize": {
        "x": 0,
        "y": 0,
        "w": 40,
        "h": 40
      },
      "sourceSize": {
        "w": 40,
        "h": 40
      },
      "pivot": {
        "x": 0.5,
        "y": 0.5
      }
    },
    "portal_27": {
      "frame": {
        "x": 641,
        "y": 253,
        "w": 40,
        "h": 40
      },
      "rotated": false,
      "trimmed": false,
      "spriteSourceSize": {
        "x": 0,
        "y": 0,
        "w": 40,
        "h": 40
      },
      "sourceSize": {
        "w": 40,
        "h": 40
      },
      "pivot": {
        "x": 0.5,
        "y": 0.5
      }
    },
    "portal_28": {
      "frame": {
        "x": 641,
        "y": 295,
        "w": 40,
        "h": 40
      },
      "rotated": false,
      "trimmed": false,
      "spriteSourceSize": {
        "x": 0,
        "y": 0,
        "w": 40,
        "h": 40
      },
      "sourceSize": {
        "w": 40,
        "h": 40
      },
      "pivot": {
        "x": 0.5,
        "y": 0.5
      }
    },
    "portal_29": {
      "frame": {
        "x": 641,
        "y": 337,
        "w": 40,
        "h": 40
      },
      "rotated": false,
      "trimmed": false,
      "spriteSourceSize": {
        "x": 0,
        "y": 0,
        "w": 40,
        "h": 40
      },
      "sourceSize": {
        "w": 40,
        "h": 40
      },
      "pivot": {
        "x": 0.5,
        "y": 0.5
      }
    },
    "portal_30": {
      "frame": {
        "x": 641,
        "y": 379,
        "w": 40,
        "h": 40
      },
      "rotated": false,
      "trimmed": false,
      "spriteSourceSize": {
        "x": 0,
        "y": 0,
        "w": 40,
        "h": 40
      },
      "sourceSize": {
        "w": 40,
        "h": 40
      },
      "pivot": {
        "x": 0.5,
        "y": 0.5
      }
    },
    "reverse_sidebar": {
      "frame": {
        "x": 641,
        "y": 421,
        "w": 40,
        "h": 40
      },
      "rotated": false,
      "trimmed": false,
      "spriteSourceSize": {
        "x": 0,
        "y": 0,
        "w": 40,
        "h": 40
      },
      "sourceSize": {
        "w": 40,
        "h": 40
      },
      "pivot": {
        "x": 0.5,
        "y": 0.5
      }
    },
    "rifle_sidebar": {
      "frame": {
        "x": 641,
        "y": 463,
        "w": 40,
        "h": 40
      },
      "rotated": false,
      "trimmed": false,
      "spriteSourceSize": {
        "x": 0,
        "y": 0,
        "w": 40,
        "h": 40
      },
      "sourceSize": {
        "w": 40,
        "h": 40
      },
      "pivot": {
        "x": 0.5,
        "y": 0.5
      }
    },
    "shield_sidebar": {
      "frame": {
        "x": 641,
        "y": 505,
        "w": 40,
        "h": 40
      },
      "rotated": false,
      "trimmed": false,
      "spriteSourceSize": {
        "x": 0,
        "y": 0,
        "w": 40,
        "h": 40
      },
      "sourceSize": {
        "w": 40,
        "h": 40
      },
      "pivot": {
        "x": 0.5,
        "y": 0.5
      }
    },
    "shotgun_sidebar": {
      "frame": {
        "x": 641,
        "y": 547,
        "w": 40,
        "h": 40
      },
      "rotated": false,
      "trimmed": false,
      "spriteSourceSize": {
        "x": 0,
        "y": 0,
        "w": 40,
        "h": 40
      },
      "sourceSize": {
        "w": 40,
        "h": 40
      },
      "pivot": {
        "x": 0.5,
        "y": 0.5
      }
    },
    "slow_sidebar": {
      "frame": {
        "x": 641,
        "y": 589,
        "w": 40,
        "h": 40
      },
      "rotated": false,
      "trimmed": false,
      "spriteSourceSize": {
        "x": 0,
        "y": 0,
        "w": 40,
        "h": 40
      },
      "sourceSize": {
        "w": 40,
        "h": 40
      },
      "pivot": {
        "x": 0.5,
        "y": 0.5
      }
    },
    "turbo_sidebar": {
      "frame": {
        "x": 641,
        "y": 631,
        "w": 40,
        "h": 40
      },
      "rotated": false,
      "trimmed": false,
      "spriteSourceSize": {
        "x": 0,
        "y": 0,
        "w": 40,
        "h": 40
      },
      "sourceSize": {
        "w": 40,
        "h": 40
      },
      "pivot": {
        "x": 0.5,
        "y": 0.5
      }
    },
    "uzi_sidebar": {
      "frame": {
        "x": 641,
        "y": 673,
        "w": 40,
        "h": 40
      },
      "rotated": false,
      "trimmed": false,
      "spriteSourceSize": {
        "x": 0,
        "y": 0,
        "w": 40,
        "h": 40
      },
      "sourceSize": {
        "w": 40,
        "h": 40
      },
      "pivot": {
        "x": 0.5,
        "y": 0.5
      }
    }
  },
  "meta": {
    "app": "http://github.com/odrick/free-tex-packer-core",
    "version": "0.3.5",
    "image": "items.png",
    "format": "RGBA8888",
    "size": {
      "w": 1024,
      "h": 1024
    },
    "scale": 1
  }
}